module_aifree/__init__.py
module_aifree/neural_network_app.py
module_aifree/python_db_prompt.txt
module_aifree/script_analysis_prompt.txt
module_aifree/system_prompt.txt
module_aifree-0.4.dist-info/METADATA
module_aifree-0.4.dist-info/WHEEL
module_aifree-0.4.dist-info/entry_points.txt
module_aifree-0.4.dist-info/top_level.txt
module_aifree-0.4.dist-info/RECORD
