Metadata-Version: 2.1
Name: module_aifree
Version: 0.4
Summary: A library for running a neural network GUI application.
Author: maga22maga44
Author-email: maga22maga44@gmail.com
Classifier: Programming Language :: Python :: 3
Classifier: License :: OSI Approved :: MIT License
Classifier: Operating System :: OS Independent
Requires-Python: >=3.6
Requires-Dist: pandas
Requires-Dist: PyQt5
Requires-Dist: g4f
Requires-Dist: black
Requires-Dist: keyboard
Requires-Dist: openpyxl
